bubble/__init__.py
bubble/cli.py
bubble/functions.py
bubble/functions_system.py
bubble/metadata.py
bubble/rules.py
bubble/transformer.py
bubble/clients/__init__.py
bubble/commands/__init__.py
bubble/commands/cmd_config.py
bubble/commands/cmd_examples.py
bubble/commands/cmd_export.py
bubble/commands/cmd_functions.py
bubble/commands/cmd_init.py
bubble/commands/cmd_listen.py
bubble/commands/cmd_manual.py
bubble/commands/cmd_pipe.py
bubble/commands/cmd_promote.py
bubble/commands/cmd_pull.py
bubble/commands/cmd_pump.py
bubble/commands/cmd_push.py
bubble/commands/cmd_rules.py
bubble/commands/cmd_stats.py
bubble/commands/cmd_transform.py
bubble/commands/cmd_upgrade.py
bubble/commands/cmd_web.py
bubble/extras/Bubble.1.gz
bubble/util/__init__.py
bubble/util/buts.py
bubble/util/cfg.py
bubble/util/cli_misc.py
bubble/util/counter.py
bubble/util/delta.py
bubble/util/escapes.py
bubble/util/examples.py
bubble/util/flat_dict.py
bubble/util/generators.py
bubble/util/inside_try.py
bubble/util/magic.py
bubble/util/profiling.py
bubble/util/value_path.py
bubble/util/zipit.py
bubble/util/dataset/__init__.py
bubble/util/dataset/convert.py
bubble/util/store/__init__.py
bubble/util/store/convert.py
bubble/util/store/storage_type_json.py
bubble/util/store/storage_type_jsonl.py
bubble-2016.8.16.dist-info/DESCRIPTION.rst
bubble-2016.8.16.dist-info/METADATA
bubble-2016.8.16.dist-info/RECORD
bubble-2016.8.16.dist-info/WHEEL
bubble-2016.8.16.dist-info/entry_points.txt
bubble-2016.8.16.dist-info/metadata.json
bubble-2016.8.16.dist-info/top_level.txt
