Metadata-Version: 1.1
Name: bubble
Version: 2016.8.16
Summary: cli tool to bubble information from one to another service, with rule based transformations ">>>"
Home-page: http://bubble.realopenit.nl
Author: Erdal Yildiz
Author-email: eyildiz@realopenit.nl
License: GPL-3.0
Keywords: bubble,api2api,transform
Platform: UNKNOWN
Classifier: Development Status :: 4 - Beta
Classifier: Intended Audience :: Developers
Classifier: Operating System :: POSIX :: Linux
Classifier: Environment :: Console
Classifier: Programming Language :: Python :: 2
Classifier: Programming Language :: Python :: 2.6
Classifier: Programming Language :: Python :: 2.7
